smpl_message_log/.DS_Store
smpl_message_log/__init__.py
smpl_message_log/apps.py
smpl_message_log/models.py
smpl_message_log/migrations/0001_initial.py
smpl_message_log/migrations/0002_auto_20200406_0610.py
smpl_message_log/migrations/__init__.py
smpl_message_log/templates/.DS_Store
smpl_message_log/templates/smpl_message_log/change_form.html
smpl_message_log-0.1.3.dist-info/LICENSE.txt
smpl_message_log-0.1.3.dist-info/METADATA
smpl_message_log-0.1.3.dist-info/WHEEL
smpl_message_log-0.1.3.dist-info/top_level.txt
smpl_message_log-0.1.3.dist-info/RECORD
