Metadata-Version: 2.1
Name: smpl-message-log
Version: 0.1.3
Summary: UNKNOWN
Home-page: https://github.com/ilya-muhortov/smpl-message-log
License: MIT
Platform: UNKNOWN
Requires-Dist: markdown
